flask_gcp_wand/__init__.py
flask_gcp_wand/decorator.py
flask_gcp_wand/appengine/__init__.py
flask_gcp_wand/appengine/app.py
flask_gcp_wand/appengine/env.py
flask_gcp_wand/appengine/header.py
flask_gcp_wand/consts/__init__.py
flask_gcp_wand/consts/oauth.py
flask_gcp_wand/consts/pubsub.py
flask_gcp_wand/firestore/__init__.py
flask_gcp_wand/firestore/firestore.py
flask_gcp_wand/model/__init__.py
flask_gcp_wand/model/message.py
flask_gcp_wand/pubsub/__init__.py
flask_gcp_wand/pubsub/publisher.py
flask_gcp_wand/pubsub/subscriber.py
flask_gcp_wand/run/__init__.py
flask_gcp_wand/run/logging.py
flask_gcp_wand/secret/__init__.py
flask_gcp_wand/secret/secret_manager.py
flask_gcp_wand/template/__init__.py
flask_gcp_wand/template/response.py
flask_gcp_wand/utils/__init__.py
flask_gcp_wand/utils/retry.py
flask_gcp_wand-0.1.14.dist-info/LICENSE
flask_gcp_wand-0.1.14.dist-info/METADATA
flask_gcp_wand-0.1.14.dist-info/WHEEL
flask_gcp_wand-0.1.14.dist-info/top_level.txt
flask_gcp_wand-0.1.14.dist-info/RECORD
