Metadata-Version: 2.1
Name: flask-gcp-wand
Version: 0.1.14
Summary: Flask library on GCP - mainly on GAE.
Home-page: http://github.com/skxeve/flask_gcp_wand
Author: Shuhei Koike
Author-email: skxeve@gmail.com
License: MIT
Keywords: Flask GCP GAE AppEngine PubSub
Platform: UNKNOWN
Classifier: Programming Language :: Python :: 3
Classifier: Programming Language :: Python :: 3.7
Classifier: License :: OSI Approved :: MIT License
Classifier: Framework :: Flask
Classifier: Environment :: Web Environment
Classifier: Topic :: Software Development :: Libraries :: Python Modules
Requires-Dist: Flask (>=1.0.2)
